{
    "KPackageStructure": "Plasma/Applet",
    "KPlugin": {
        "Authors": [
            {
                "Email": "zinczorphin@email.com",
                "Name": "Jack Faith"
            }
        ],
        "Category": "Multimedia",
        "Description": "Media player control widget with album art, track info and interactive controls, in Nothing style",
        "EnabledByDefault": true,
        "Icon": "/icon.png",
        "Id": "com.jaxparrow07.nothingkdewidgets.media",
        "License": "GPL-3.0",
        "Name": "Nothing Media",
        "Version": "1.1",
        "Website": "https://github.com/jaxparrow07/nothing-kde-widgets"
    },
    "X-Plasma-API-Minimum-Version": "6.0"
}
